ai_playground.py
config.py
ai_playground-0.1.1.dist-info/entry_points.txt
ai_playground-0.1.1.dist-info/LICENSE
ai_playground-0.1.1.dist-info/METADATA
ai_playground-0.1.1.dist-info/WHEEL
ai_playground-0.1.1.dist-info/RECORD
