Metadata-Version: 2.1
Name: ai-playground
Version: 0.1.1
Summary: AI Playground for trying out LLM Models, Embeddings, Vector Stores, Semantic Search, RAG, Azure OpenAI, LLaMa, Mistral
License: MIT
Author: vs4vijay
Author-email: vs4vijay@gmail.com
Requires-Python: >=3.10,<4.0
Classifier: License :: OSI Approved :: MIT License
Classifier: Programming Language :: Python :: 3
Classifier: Programming Language :: Python :: 3.10
Classifier: Programming Language :: Python :: 3.11
Classifier: Programming Language :: Python :: 3.12
Requires-Dist: python-dotenv (>=1.0.1,<2.0.0)
Requires-Dist: streamlit (>=1.34.0,<2.0.0)
